Workbook

Sheet RAW Data
A1: Year | B1: S&P Composite Price Index | C1: S&P Composite Dividends | D1: S&P Composite Earnings | E1: CPI Level (Dec 31st) | F1: 1 Year Treasury Yield (Annualized) | G1: 5 Year Treasury Yield (Annualized) | H1: S&P Composite Price Index (2024) | I1: S&P Composite Dividends (2024) | J1: S&P Composite Earnings (2024) | K1: 10-Year Avg Real Earnings | L1: Real CAPE | M1: Nominal Annual Return | N1: Real Annual Return | O1: Future 1-Year Nominal Return | P1: Future 1-Year Real Return | Q1: Future 5-Year Nominal Return | R1: Future 5-Year Real Return | T1: Previous Year CAPE | U1: S&P 500 Weight | V1: T-bill Weight | W1: Strategy Return | X1: 60/40 Benchmark Return
A2: 1922 | B2: 8.9
A3: 1923 | B3: 8.83 | C3: 0.53 | D3: 0.98 | E3: 17.3 | H3: =B3 / E3 * $E$104 -> 161.08625 | I3: =C3 / E3 * $E$104 -> 9.6688237 | J3: =D3 / E3 * $E$104 -> 17.878202 | M3: =(B3-B2+C3)/B2 -> 0.051685393 | O3: =M4 -> 0.26047565 | P3: =N4 -> 0.26047565 | Q3: =((1+M4)*(1+M5)*(1+M6)*(1+M7)*(1+M8))^(1/5)-1 -> 0.28632384 | R3: =((1+N4)*(1+N5)*(1+N6)*(1+N7)*(1+N8))^(1/5)-1 -> 0.2893188
A4: 1924 | B4: 10.58 | C4: 0.55 | D4: 0.93 | E4: 17.3 | H4: =B4 / E4 * $E$104 -> 193.01161 | I4: =C4 / E4 * $E$104 -> 10.033685 | J4: =D4 / E4 * $E$104 -> 16.966049 | M4: =(B4-B3+C4)/B3 -> 0.26047565 | N4: =(H4-H3+I4)/H3 -> 0.26047565 | O4: =M5 -> 0.25236295 | P4: =N5 -> 0.2103843 | Q4: =((1+M5)*(1+M6)*(1+M7)*(1+M8)*(1+M9))^(1/5)-1 -> 0.20579037 | R4: =((1+N5)*(1+N6)*(1+N7)*(1+N8)*(1+N9))^(1/5)-1 -> 0.2071892
A5: 1925 | B5: 12.65 | C5: 0.6 | D5: 1.25 | E5: 17.9 | H5: =B5 / E5 * $E$104 -> 223.03929 | I5: =C5 / E5 * $E$104 -> 10.578939 | J5: =D5 / E5 * $E$104 -> 22.039455 | M5: =(B5-B4+C5)/B4 -> 0.25236295 | N5: =(H5-H4+I5)/H4 -> 0.2103843 | O5: =M6 -> 0.11383399 | P5: =N6 -> 0.12641969 | Q5: =((1+M6)*(1+M7)*(1+M8)*(1+M9)*(1+M10))^(1/5)-1 -> 0.097182758 | R5: =((1+N6)*(1+N7)*(1+N8)*(1+N9)*(1+N10))^(1/5)-1 -> 0.12068718
A6: 1926 | B6: 13.4 | C6: 0.69 | D6: 1.24 | E6: 17.7 | H6: =B6 / E6 * $E$104 -> 238.9326 | I6: =C6 / E6 * $E$104 -> 12.303246 | J6: =D6 / E6 * $E$104 -> 22.110181 | M6: =(B6-B5+C6)/B5 -> 0.11383399 | N6: =(H6-H5+I6)/H5 -> 0.12641969 | O6: =M7 -> 0.36567164 | P6: =N7 -> 0.39724786 | Q6: =((1+M7)*(1+M8)*(1+M9)*(1+M10)*(1+M11))^(1/5)-1 -> -0.040160777 | R6: =((1+N7)*(1+N8)*(1+N9)*(1+N10)*(1+N11))^(1/5)-1 -> -0.0024777874
A7: 1927 | B7: 17.53 | C7: 0.77 | D7: 1.11 | E7: 17.3 | H7: =B7 / E7 * $E$104 -> 319.8009 | I7: =C7 / E7 * $E$104 -> 14.047159 | J7: =D7 / E7 * $E$104 -> 20.249801 | M7: =(B7-B6+C7)/B6 -> 0.36567164 | N7: =(H7-H6+I7)/H6 -> 0.39724786 | O7: =M8 -> 0.46662864 | P7: =N8 -> 0.48378219 | Q7: =((1+M8)*(1+M9)*(1+M10)*(1+M11)*(1+M12))^(1/5)-1 -> -0.11414637 | R7: =((1+N8)*(1+N9)*(1+N10)*(1+N11)*(1+N12))^(1/5)-1 -> -0.063480266
A8: 1928 | B8: 24.86 | C8: 0.85 | D8: 1.38 | E8: 17.1 | H8: =B8 / E8 * $E$104 -> 458.82692 | I8: =C8 / E8 * $E$104 -> 15.687968 | J8: =D8 / E8 * $E$104 -> 25.469877 | M8: =(B8-B7+C8)/B7 -> 0.46662864 | N8: =(H8-H7+I8)/H7 -> 0.48378219 | O8: =M9 -> -0.08769107 | P8: =N9 -> -0.092995192 | Q8: =((1+M9)*(1+M10)*(1+M11)*(1+M12)*(1+M13))^(1/5)-1 -> -0.1044514 | R8: =((1+N9)*(1+N10)*(1+N11)*(1+N12)*(1+N13))^(1/5)-1 -> -0.056865577
A9: 1929 | B9: 21.71 | C9: 0.97 | D9: 1.61 | E9: 17.2 | H9: =B9 / E9 * $E$104 -> 398.35957 | I9: =C9 / E9 * $E$104 -> 17.798654 | J9: =D9 / E9 * $E$104 -> 29.542096 | M9: =(B9-B8+C9)/B8 -> -0.08769107 | N9: =(H9-H8+I9)/H8 -> -0.092995192 | O9: =M10 -> -0.21879318 | P9: =N10 -> -0.1654188 | Q9: =((1+M10)*(1+M11)*(1+M12)*(1+M13)*(1+M14))^(1/5)-1 -> -0.10270241 | R9: =((1+N10)*(1+N11)*(1+N12)*(1+N13)*(1+N14))^(1/5)-1 -> -0.05676213
A10: 1930 | B10: 15.98 | C10: 0.98 | D10: 0.97 | E10: 16.1 | H10: =B10 / E10 * $E$104 -> 313.25266 | I10: =C10 / E10 * $E$104 -> 19.210739 | J10: =D10 / E10 * $E$104 -> 19.014711 | M10: =(B10-B9+C10)/B9 -> -0.21879318 | N10: =(H10-H9+I10)/H9 -> -0.1654188 | O10: =M11 -> -0.42928661 | P10: =N11 -> -0.37065167 | Q10: =((1+M11)*(1+M12)*(1+M13)*(1+M14)*(1+M15))^(1/5)-1 -> 0.027311328 | R10: =((1+N11)*(1+N12)*(1+N13)*(1+N14)*(1+N15))^(1/5)-1 -> 0.05947676
A11: 1931 | B11: 8.3 | C11: 0.82 | D11: 0.61 | E11: 14.6 | H11: =B11 / E11 * $E$104 -> 179.41928 | I11: =C11 / E11 * $E$104 -> 17.72576 | J11: =D11 / E11 * $E$104 -> 13.186236 | M11: =(B11-B10+C11)/B10 -> -0.42928661 | N11: =(H11-H10+I11)/H10 -> -0.37065167 | O11: =M12 -> -0.085542169 | P11: =N12 -> 0.019166743 | Q11: =((1+M12)*(1+M13)*(1+M14)*(1+M15)*(1+M16))^(1/5)-1 -> 0.21683711 | R11: =((1+N12)*(1+N13)*(1+N14)*(1+N15)*(1+N16))^(1/5)-1 -> 0.22709281
A12: 1932 | B12: 7.09 | C12: 0.5 | D12: 0.41 | E12: 13.1 | H12: =B12 / E12 * $E$104 -> 170.81217 | I12: =C12 / E12 * $E$104 -> 12.045992 | J12: =D12 / E12 * $E$104 -> 9.8777137 | K12: =AVERAGE(J3:J12) -> 19.633432 | L12: =H12/K12 -> 8.7000668 | M12: =(B12-B11+C12)/B11 -> -0.085542169 | N12: =(H12-H11+I12)/H11 -> 0.019166743 | O12: =M13 -> 0.54866008 | P12: =N13 -> 0.53692781 | Q12: =((1+M13)*(1+M14)*(1+M15)*(1+M16)*(1+M17))^(1/5)-1 -> 0.14967575 | R12: =((1+N13)*(1+N14)*(1+N15)*(1+N16)*(1+N17))^(1/5)-1 -> 0.12812476
A13: 1933 | B13: 10.54 | C13: 0.44 | D13: 0.44 | E13: 13.2 | F13: 0.0035 | G13: 0.0135 | H13: =B13 / E13 * $E$104 -> 252.00581 | I13: =C13 / E13 * $E$104 -> 10.520167 | J13: =D13 / E13 * $E$104 -> 10.520167 | K13: =AVERAGE(J4:J13) -> 18.897629 | L13: =H13/K13 -> 13.335314 | M13: =(B13-B12+C13)/B12 -> 0.54866008 | N13: =(H13-H12+I13)/H12 -> 0.53692781 | O13: =M14 -> -0.078747628 | P13: =N14 -> -0.092497663 | Q13: =((1+M14)*(1+M15)*(1+M16)*(1+M17)*(1+M18))^(1/5)-1 -> 0.083295871 | R13: =((1+N14)*(1+N15)*(1+N16)*(1+N17)*(1+N18))^(1/5)-1 -> 0.070622255 | T13: =L12 -> 8.7000668 | U13: =IF(T13<15,0.8,IF(T13>25,0.3,0.6)) -> 0.8 | V13: =1-U13 -> 0.2 | W13: =U13*M13+V13*F13 -> 0.43962807 | X13: =0.6*M13+0.4*F13 -> 0.33059605
A14: 1934 | B14: 9.26 | C14: 0.45 | D14: 0.49 | E14: 13.4 | F14: 0.0027833333 | G14: 0.0148 | H14: =B14 / E14 * $E$104 -> 218.09719 | I14: =C14 / E14 * $E$104 -> 10.598675 | J14: =D14 / E14 * $E$104 -> 11.54078 | K14: =AVERAGE(J5:J14) -> 18.355102 | L14: =H14/K14 -> 11.882102 | M14: =(B14-B13+C14)/B13 -> -0.078747628 | N14: =(H14-H13+I14)/H13 -> -0.092497663 | O14: =M15 -> 0.53671706 | P14: =N15 -> 0.49217454 | Q14: =((1+M15)*(1+M16)*(1+M17)*(1+M18)*(1+M19))^(1/5)-1 -> 0.10851574 | R14: =((1+N15)*(1+N16)*(1+N17)*(1+N18)*(1+N19))^(1/5)-1 -> 0.098846974 | T14: =L13 -> 13.335314 | U14: =IF(T14<15,0.8,IF(T14>25,0.3,0.6)) -> 0.8 | V14: =1-U14 -> 0.2 | W14: =U14*M14+V14*F14 -> -0.062441436 | X14: =0.6*M14+0.4*F14 -> -0.046135244
A15: 1935 | B15: 13.76 | C15: 0.47 | D15: 0.76 | E15: 13.8 | F15: 0.001675 | G15: 0.0135 | H15: =B15 / E15 * $E$104 -> 314.6902 | I15: =C15 / E15 * $E$104 -> 10.748866 | J15: =D15 / E15 * $E$104 -> 17.381145 | K15: =AVERAGE(J6:J15) -> 17.889271 | L15: =H15/K15 -> 17.591002 | M15: =(B15-B14+C15)/B14 -> 0.53671706 | N15: =(H15-H14+I15)/H14 -> 0.49217454 | O15: =M16 -> 0.3306686 | P15: =N16 -> 0.31165905 | Q15: =((1+M16)*(1+M17)*(1+M18)*(1+M19)*(1+M20))^(1/5)-1 -> -0.0012871671 | R15: =((1+N16)*(1+N17)*(1+N18)*(1+N19)*(1+N20))^(1/5)-1 -> -0.0055736465 | T15: =L14 -> 11.882102 | U15: =IF(T15<15,0.8,IF(T15>25,0.3,0.6)) -> 0.8 | V15: =1-U15 -> 0.2 | W15: =U15*M15+V15*F15 -> 0.42970865 | X15: =0.6*M15+0.4*F15 -> 0.32270024
A16: 1936 | B16: 17.59 | C16: 0.72 | D16: 1.02 | E16: 14 | F16: 0.001725 | G16: 0.0147 | H16: =B16 / E16 * $E$104 -> 396.53514 | I16: =C16 / E16 * $E$104 -> 16.231114 | J16: =D16 / E16 * $E$104 -> 22.994079 | K16: =AVERAGE(J7:J16) -> 17.97766 | L16: =H16/K16 -> 22.057105 | M16: =(B16-B15+C16)/B15 -> 0.3306686 | N16: =(H16-H15+I16)/H15 -> 0.31165905 | O16: =M17 -> -0.31154065 | P16: =N17 -> -0.33066452 | Q16: =((1+M17)*(1+M18)*(1+M19)*(1+M20)*(1+M21))^(1/5)-1 -> -0.073614896 | R16: =((1+N17)*(1+N18)*(1+N19)*(1+N20)*(1+N21))^(1/5)-1 -> -0.092282244 | T16: =L15 -> 17.591002 | U16: =IF(T16<15,0.8,IF(T16>25,0.3,0.6)) -> 0.6 | V16: =1-U16 -> 0.4 | W16: =U16*M16+V16*F16 -> 0.19909116 | X16: =0.6*M16+0.4*F16 -> 0.19909116
A17: 1937 | B17: 11.31 | C17: 0.8 | D17: 1.13 | E17: 14.4 | F17: 0.0027583333 | G17: 0.0158 | H17: =B17 / E17 * $E$104 -> 247.88143 | I17: =C17 / E17 * $E$104 -> 17.533611 | J17: =D17 / E17 * $E$104 -> 24.766226 | K17: =AVERAGE(J8:J17) -> 18.429303 | L17: =H17/K17 -> 13.450396 | M17: =(B17-B16+C17)/B16 -> -0.31154065 | N17: =(H17-H16+I17)/H16 -> -0.33066452 | O17: =M18 -> 0.15030946 | P17: =N18 -> 0.18317545 | Q17: =((1+M18)*(1+M19)*(1+M20)*(1+M21)*(1+M22))^(1/5)-1 -> 0.034569953 | R17: =((1+N18)*(1+N19)*(1+N20)*(1+N21)*(1+N22))^(1/5)-1 -> 0.0019706925 | T17: =L16 -> 22.057105 | U17: =IF(T17<15,0.8,IF(T17>25,0.3,0.6)) -> 0.6 | V17: =1-U17 -> 0.4 | W17: =U17*M17+V17*F17 -> -0.18582106 | X17: =0.6*M17+0.4*F17 -> -0.18582106
A18: 1938 | B18: 12.5 | C18: 0.51 | D18: 0.64 | E18: 14 | F18: 0.00065 | G18: 0.0127 | H18: =B18 / E18 * $E$104 -> 281.79018 | I18: =C18 / E18 * $E$104 -> 11.497039 | J18: =D18 / E18 * $E$104 -> 14.427657 | K18: =AVERAGE(J9:J18) -> 17.325081 | L18: =H18/K18 -> 16.264869 | M18: =(B18-B17+C18)/B17 -> 0.15030946 | N18: =(H18-H17+I18)/H17 -> 0.18317545 | O18: =M19 -> 0.0336 | P18: =N19 -> 0.0336 | Q18: =((1+M19)*(1+M20)*(1+M21)*(1+M22)*(1+M23))^(1/5)-1 -> 0.049354666 | R18: =((1+N19)*(1+N20)*(1+N21)*(1+N22)*(1+N23))^(1/5)-1 -> 0.0047038247 | T18: =L17 -> 13.450396 | U18: =IF(T18<15,0.8,IF(T18>25,0.3,0.6)) -> 0.8 | V18: =1-U18 -> 0.2 | W18: =U18*M18+V18*F18 -> 0.12037757 | X18: =0.6*M18+0.4*F18 -> 0.090445676
A19: 1939 | B19: 12.3 | C19: 0.62 | D19: 0.9 | E19: 14 | F19: 0.00045833333 | G19: 0.0135 | H19: =B19 / E19 * $E$104 -> 277.28154 | I19: =C19 / E19 * $E$104 -> 13.976793 | J19: =D19 / E19 * $E$104 -> 20.288893 | K19: =AVERAGE(J10:J19) -> 16.399761 | L19: =H19/K19 -> 16.907657 | M19: =(B19-B18+C19)/B18 -> 0.0336 | N19: =(H19-H18+I19)/H18 -> 0.0336 | O19: =M20 -> -0.087804878 | P19: =N20 -> -0.094274347 | Q19: =((1+M20)*(1+M21)*(1+M22)*(1+M23)*(1+M24))^(1/5)-1 -> 0.079783185 | R19: =((1+N20)*(1+N21)*(1+N22)*(1+N23)*(1+N24))^(1/5)-1 -> 0.029148788 | T19: =L18 -> 16.264869 | U19: =IF(T19<15,0.8,IF(T19>25,0.3,0.6)) -> 0.6 | V19: =1-U19 -> 0.4 | W19: =U19*M19+V19*F19 -> 0.020343333 | X19: =0.6*M19+0.4*F19 -> 0.020343333
A20: 1940 | B20: 10.55 | C20: 0.67 | D20: 1.05 | E20: 14.1 | F20: 0.00035833333 | G20: 0.0134 | H20: =B20 / E20 * $E$104 -> 236.14417 | I20: =C20 / E20 * $E$104 -> 14.996833 | J20: =D20 / E20 * $E$104 -> 23.5025 | K20: =AVERAGE(J11:J20) -> 16.84854 | L20: =H20/K20 -> 14.015705 | M20: =(B20-B19+C20)/B19 -> -0.087804878 | N20: =(H20-H19+I20)/H19 -> -0.094274347 | O20: =M21 -> -0.086255924 | P20: =N21 -> -0.16878765 | Q20: =((1+M21)*(1+M22)*(1+M23)*(1+M24)*(1+M25))^(1/5)-1 -> 0.1737943 | R20: =((1+N21)*(1+N22)*(1+N23)*(1+N24)*(1+N25))^(1/5)-1 -> 0.11537663 | T20: =L19 -> 16.907657 | U20: =IF(T20<15,0.8,IF(T20>25,0.3,0.6)) -> 0.6 | V20: =1-U20 -> 0.4 | W20: =U20*M20+V20*F20 -> -0.052539593 | X20: =0.6*M20+0.4*F20 -> -0.052539593
A21: 1941 | B21: 8.93 | C21: 0.71 | D21: 1.16 | E21: 15.5 | F21: 0.0011 | G21: 0.01478067 | H21: =B21 / E21 * $E$104 -> 181.8292 | I21: =C21 / E21 * $E$104 -> 14.456745 | J21: =D21 / E21 * $E$104 -> 23.619471 | K21: =AVERAGE(J12:J21) -> 17.891863 | L21: =H21/K21 -> 10.162676 | M21: =(B21-B20+C21)/B20 -> -0.086255924 | N21: =(H21-H20+I21)/H20 -> -0.16878765 | O21: =M22 -> 0.19596865 | P21: =N22 -> 0.096894319 | Q21: =((1+M22)*(1+M23)*(1+M24)*(1+M25)*(1+M26))^(1/5)-1 -> 0.16590922 | R21: =((1+N22)*(1+N23)*(1+N24)*(1+N25)*(1+N26))^(1/5)-1 -> 0.092052164 | T21: =L20 -> 14.015705 | U21: =IF(T21<15,0.8,IF(T21>25,0.3,0.6)) -> 0.8 | V21: =1-U21 -> 0.2 | W21: =U21*M21+V21*F21 -> -0.068784739 | X21: =0.6*M21+0.4*F21 -> -0.051313555
A22: 1942 | B22: 10.09 | C22: 0.59 | D22: 1.03 | E22: 16.9 | F22: 0.0043 | G22: 0.017288844 | H22: =B22 / E22 * $E$104 -> 188.42926 | I22: =C22 / E22 * $E$104 -> 11.018163 | J22: =D22 / E22 * $E$104 -> 19.235098 | K22: =AVERAGE(J13:J22) -> 18.827601 | L22: =H22/K22 -> 10.008139 | M22: =(B22-B21+C22)/B21 -> 0.19596865 | N22: =(H22-H21+I22)/H21 -> 0.096894319 | O22: =M23 -> 0.23488603 | P22: =N23 -> 0.1994008 | Q22: =((1+M23)*(1+M24)*(1+M25)*(1+M26)*(1+M27))^(1/5)-1 -> 0.13164116 | R22: =((1+N23)*(1+N24)*(1+N25)*(1+N26)*(1+N27))^(1/5)-1 -> 0.060334527 | T22: =L21 -> 10.162676 | U22: =IF(T22<15,0.8,IF(T22>25,0.3,0.6)) -> 0.8 | V22: =1-U22 -> 0.2 | W22: =U22*M22+V22*F22 -> 0.15763492 | X22: =0.6*M22+0.4*F22 -> 0.11930119
A23: 1943 | B23: 11.85 | C23: 0.61 | D23: 0.94 | E23: 17.4 | F23: 0.0084 | G23: 0.016500042 | H23: =B23 / E23 * $E$104 -> 214.93789 | I23: =C23 / E23 * $E$104 -> 11.064313 | J23: =D23 / E23 * $E$104 -> 17.049925 | K23: =AVERAGE(J14:J23) -> 19.480577 | L23: =H23/K23 -> 11.033446 | M23: =(B23-B22+C23)/B22 -> 0.23488603 | N23: =(H23-H22+I23)/H22 -> 0.1994008 | O23: =M24 -> 0.19240506 | P23: =N24 -> 0.16560944 | Q23: =((1+M24)*(1+M25)*(1+M26)*(1+M27)*(1+M28))^(1/5)-1 -> 0.10545061 | R23: =((1+N24)*(1+N25)*(1+N26)*(1+N27)*(1+N28))^(1/5)-1 -> 0.035728165 | T23: =L22 -> 10.008139 | U23: =IF(T23<15,0.8,IF(T23>25,0.3,0.6)) -> 0.8 | V23: =1-U23 -> 0.2 | W23: =U23*M23+V23*F23 -> 0.18958882 | X23: =0.6*M23+0.4*F23 -> 0.14429162
A24: 1944 | B24: 13.49 | C24: 0.64 | D24: 0.93 | E24: 17.8 | F24: 0.0087 | G24: 0.014987802 | H24: =B24 / E24 * $E$104 -> 239.18604 | I24: =C24 / E24 * $E$104 -> 11.347596 | J24: =D24 / E24 * $E$104 -> 16.489475 | K24: =AVERAGE(J15:J24) -> 19.975447 | L24: =H24/K24 -> 11.974002 | M24: =(B24-B23+C24)/B23 -> 0.19240506 | N24: =(H24-H23+I24)/H23 -> 0.16560944 | O24: =M25 -> 0.38472943 | P24: =N25 -> 0.35429582 | Q24: =((1+M25)*(1+M26)*(1+M27)*(1+M28)*(1+M29))^(1/5)-1 -> 0.10186223 | R24: =((1+N25)*(1+N26)*(1+N27)*(1+N28)*(1+N29))^(1/5)-1 -> 0.041427153 | T24: =L23 -> 11.033446 | U24: =IF(T24<15,0.8,IF(T24>25,0.3,0.6)) -> 0.8 | V24: =1-U24 -> 0.2 | W24: =U24*M24+V24*F24 -> 0.15566405 | X24: =0.6*M24+0.4*F24 -> 0.11892304
... A99: 2019 | B99: 3176.7495 | C99: 58.24 | D99: 139.47 | E99: 256.974 | F99: 0.0266 | G99: 0.0268 | H99: =B99 / E99 * $E$104 -> 3901.5544 | I99: =C99 / E99 * $E$104 -> 71.527996 | J99: =D99 / E99 * $E$104 -> 171.29137 | K99: =AVERAGE(J90:J99) -> 134.24343 | L99: =H99/K99 -> 29.063279 | M99: =(B99-B98+C99)/B98 -> 0.26006969 | N99: =(H99-H98+I99)/H98 -> 0.23191875 | O99: =M100 -> 0.18158162 | P99: =N100 -> 0.16570466 | Q99: =((1+M100)*(1+M101)*(1+M102)*(1+M103)*(1+M104))^(1/5)-1 -> 0.15267565 | R99: =((1+N100)*(1+N101)*(1+N102)*(1+N103)*(1+N104))^(1/5)-1 -> 0.10625738 | T99: =L98 -> 25.891359 | U99: =IF(T99<15,0.8,IF(T99>25,0.3,0.6)) -> 0.3 | V99: =1-U99 -> 0.7 | W99: =U99*M99+V99*F99 -> 0.096640908 | X99: =0.6*M99+0.4*F99 -> 0.16668182
A100: 2020 | B100: 3695.31 | C100: 58.278846 | D100: 94.13 | E100: 260.474 | F100: 0.0155 | G100: 0.0168 | H100: =B100 / E100 * $E$104 -> 4477.4462 | I100: =C100 / E100 * $E$104 -> 70.613939 | J100: =D100 / E100 * $E$104 -> 114.05322 | K100: =AVERAGE(J91:J100) -> 134.51081 | L100: =H100/K100 -> 33.286888 | M100: =(B100-B99+C100)/B99 -> 0.18158162 | N100: =(H100-H99+I100)/H99 -> 0.16570466 | O100: =M101 -> 0.28139989 | P100: =N101 -> 0.1971627 | T100: =L99 -> 29.063279 | U100: =IF(T100<15,0.8,IF(T100>25,0.3,0.6)) -> 0.3 | V100: =1-U100 -> 0.7 | W100: =U100*M100+V100*F100 -> 0.065324486 | X100: =0.6*M100+0.4*F100 -> 0.11514897
A101: 2021 | B101: 4674.7727 | C101: 60.397117 | D101: 197.87 | E101: 278.802 | F101: 0.001 | G101: 0.0036 | H101: =B101 / E101 * $E$104 -> 5291.8618 | I101: =C101 / E101 * $E$104 -> 68.369783 | J101: =D101 / E101 * $E$104 -> 223.98965 | K101: =AVERAGE(J92:J101) -> 144.74971 | L101: =H101/K101 -> 36.558704 | M101: =(B101-B100+C101)/B100 -> 0.28139989 | N101: =(H101-H100+I101)/H100 -> 0.1971627 | O101: =M102 -> -0.14877125 | P101: =N102 -> -0.20038182 | T101: =L100 -> 33.286888 | U101: =IF(T101<15,0.8,IF(T101>25,0.3,0.6)) -> 0.3 | V101: =1-U101 -> 0.7 | W101: =U101*M101+V101*F101 -> 0.085119968 | X101: =0.6*M101+0.4*F101 -> 0.16923994
A102: 2022 | B102: 3912.381 | C102: 66.92 | D102: 172.75 | E102: 296.797 | F102: 0.004 | G102: 0.0127 | H102: =B102 / E102 * $E$104 -> 4160.3082 | I102: =C102 / E102 * $E$104 -> 71.160715 | J102: =D102 / E102 * $E$104 -> 183.69715 | K102: =AVERAGE(J93:J102) -> 151.22793 | L102: =H102/K102 -> 27.510184 | M102: =(B102-B101+C102)/B101 -> -0.14877125 | N102: =(H102-H101+I102)/H101 -> -0.20038182 | O102: =M103 -> 0.21546323 | P102: =N103 -> 0.1760409 | T102: =L101 -> 36.558704 | U102: =IF(T102<15,0.8,IF(T102>25,0.3,0.6)) -> 0.3 | V102: =1-U102 -> 0.7 | W102: =U102*M102+V102*F102 -> -0.041831375 | X102: =0.6*M102+0.4*F102 -> -0.087662749
A103: 2023 | B103: 4685.0515 | C103: 70.303692 | D103: 192.43 | E103: 306.746 | F103: 0.0471 | G103: 0.0399 | H103: =B103 / E103 * $E$104 -> 4820.3585 | I103: =C103 / E103 * $E$104 -> 72.334103 | J103: =D103 / E103 * $E$104 -> 197.98749 | K103: =AVERAGE(J94:J103) -> 157.45716 | L103: =H103/K103 -> 30.613777 | M103: =(B103-B102+C103)/B102 -> 0.21546323 | N103: =(H103-H102+I103)/H102 -> 0.1760409 | O103: =M104 -> 0.29896989 | P103: =N104 -> 0.26250794 | T103: =L102 -> 27.510184 | U103: =IF(T103<15,0.8,IF(T103>25,0.3,0.6)) -> 0.3 | V103: =1-U103 -> 0.7 | W103: =U103*M103+V103*F103 -> 0.097608969 | X103: =0.6*M103+0.4*F103 -> 0.14811794
A104: 2024 | B104: 6010.9086 | C104: 74.832255 | D104: 210.17 | E104: 315.605 | F104: 0.0479 | G104: 0.039 | H104: =B104 / E104 * $E$104 -> 6010.9086 | I104: =C104 / E104 * $E$104 -> 74.832255 | J104: =D104 / E104 * $E$104 -> 210.17 | K104: =AVERAGE(J95:J104) -> 164.72293 | L104: =H104/K104 -> 36.491025 | M104: =(B104-B103+C104)/B103 -> 0.29896989 | N104: =(H104-H103+I104)/H103 -> 0.26250794 | T104: =L103 -> 30.613777 | U104: =IF(T104<15,0.8,IF(T104>25,0.3,0.6)) -> 0.3 | V104: =1-U104 -> 0.7 | W104: =U104*M104+V104*F104 -> 0.12322097 | X104: =0.6*M104+0.4*F104 -> 0.19854193
A105: Average | L105: =AVERAGE(L12:L104) -> 18.962843 | M105: =AVERAGE(M3:M104) -> 0.12151589 | N105: =AVERAGE(N4:N104) -> 0.091047917 | T105: =AVERAGE(T13:T104) -> 18.772319 | U105: =AVERAGE(U13:U104) -> 0.60108696 | V105: =AVERAGE(V13:V104) -> 0.39891304 | W105: =AVERAGE(W13:W104) -> 0.097397241 | X105: =AVERAGE(X13:X104) -> 0.091293139
T108: Based on the regression results, CAPE has a negative relationship with future returns and stronger predictive power over longer horizons. Therefore, I use the previous year’s CAPE ratio as a signal for asset allocation. When CAPE is low, indicating undervaluation, I allocate 80% to the S&P 500 and 20% to Treasury bills. When CAPE is between 15 and 25, I allocate 60% to equities and 40% to Treasury bills. When CAPE is high, indicating overvaluation, I reduce equity exposure to 30% and invest 70% in Treasury bills. This strategy is based on the idea that investors should increase equity exposure when the market is undervalued and reduce exposure when it is overvalued. Based on my calculations, the strategy generates an average return of about 4%, compared to about 3% for the static 60/40 benchmark. Therefore, the CAPE-based market-timing strategy slightly outperforms the benchmark.

Sheet Regression
A1: Y1real | K1: Y5real
A2: Summary Output | K2: Summary Output
A4: Regression Statistics | K4: Regression Statistics
A5: Multiple R | B5: 0.18158939 | K5: Multiple R | L5: 0.35844923
A6: R Square | B6: 0.032974708 | K6: R Square | L6: 0.12848585
A7: Adjusted R Square | B7: 0.022109255 | K7: Adjusted R Square | L7: 0.11823275
A8: Standard Error | B8: 0.17060306 | K8: Standard Error | L8: 0.069021464
A9: Observations | B9: 91 | K9: Observations | L9: 87
A11: ANOVA | K11: ANOVA
B12: df | C12: SS | D12: MS | E12: F | F12: Significance F | L12: df | M12: SS | N12: MS | O12: F | P12: Significance F
A13: Regression | B13: 1 | C13: 0.088329699 | D13: 0.088329699 | E13: 3.0348213 | F13: 0.084950167 | K13: Regression | L13: 1 | M13: 0.059699147 | N13: 0.059699147 | O13: 12.531406 | P13: 0.00065186793
A14: Residual | B14: 89 | C14: 2.5903809 | D14: 0.029105403 | K14: Residual | L14: 85 | M14: 0.40493681 | N14: 0.0047639624
A15: total | B15: 90 | C15: 2.6787106 | K15: total | L15: 86 | M15: 0.46463595
B17: Coefficients | C17: Standard Error | D17: t Stat | E17: P-value | F17: Lower 95% | G17: Upper 95% | H17: Lower 95.0% | I17: Upper 95.0% | L17: Coefficients | M17: Standard Error | N17: t Stat | O17: P-value | P17: Lower 95% | Q17: Upper 95% | R17: Lower 95.0% | S17: Upper 95.0%
A18: Intercept | B18: 0.16232285 | C18: 0.04752849 | D18: 3.4152747 | E18: 0.00096172831 | F18: 0.06788475 | G18: 0.25676094 | H18: 0.06788475 | I18: 0.25676094 | K18: Intercept | L18: 0.1376275 | M18: 0.020042775 | N18: 6.8666888 | O18: 1.0137007e-09 | P18: 0.097777091 | Q18: 0.1774779 | R18: 0.097777091 | S18: 0.1774779
A19: 8.7000668 | B19: -0.0040625393 | C19: 0.0023320132 | D19: -1.7420739 | E19: 0.084950167 | F19: -0.0086962 | G19: 0.00057112132 | H19: -0.0086962 | I19: 0.00057112132 | K19: 8.7000668 | L19: -0.0036070616 | M19: 0.0010189519 | N19: -3.5399726 | O19: 0.00065186793 | P19: -0.0056330109 | Q19: -0.0015811123 | R19: -0.0056330109 | S19: -0.0015811123
A25: Y1normal | K25: y5 normal
A26: Summary Output | K26: Summary Output
A28: Regression Statistics | K28: Regression Statistics
A29: Multiple R | B29: 0.23587842 | K29: Multiple R | L29: 0.50206881
A30: R Square | B30: 0.055638627 | K30: R Square | L30: 0.25207309
A31: Adjusted R Square | B31: 0.045027826 | K31: Adjusted R Square | L31: 0.24327395
A32: Standard Error | B32: 0.1653601 | K32: Standard Error | L32: 0.060943146
A33: Observations | B33: 91 | K33: Observations | L33: 87
A35: ANOVA | K35: ANOVA
B36: df | C36: SS | D36: MS | E36: F | F36: Significance F | L36: df | M36: SS | N36: MS | O36: F | P36: Significance F
A37: Regression | B37: 1 | C37: 0.14338035 | D37: 0.14338035 | E37: 5.2435836 | F37: 0.024392282 | K37: Regression | L37: 1 | M37: 0.10639862 | N37: 0.10639862 | O37: 28.647469 | P37: 7.2520361e-07
A38: Residual | B38: 89 | C38: 2.4336126 | D38: 0.027343962 | K38: Residual | L38: 85 | M38: 0.3156957 | N38: 0.003714067
A39: total | B39: 90 | C39: 2.576993 | K39: total | L39: 86 | M39: 0.42209432
B41: Coefficients | C41: Standard Error | D41: t Stat | E41: P-value | F41: Lower 95% | G41: Upper 95% | H41: Lower 95.0% | I41: Upper 95.0% | L41: Coefficients | M41: Standard Error | N41: t Stat | O41: P-value | P41: Lower 95% | Q41: Upper 95% | R41: Lower 95.0% | S41: Upper 95.0%
A42: Intercept | B42: 0.22033742 | C42: 0.046067848 | D42: 4.7828893 | E42: 6.8048685e-06 | F42: 0.12880159 | G42: 0.31187325 | H42: 0.12880159 | I42: 0.31187325 | K42: Intercept | L42: 0.1975988 | M42: 0.017696955 | N42: 11.165695 | O42: 2.4003136e-18 | P42: 0.16241252 | Q42: 0.23278509 | R42: 0.16241252 | S42: 0.23278509
A43: 8.7000668 | B43: -0.0051759375 | C43: 0.002260346 | D43: -2.2898873 | E43: 0.024392282 | F43: -0.0096671969 | G43: -0.00068467814 | H43: -0.0096671969 | I43: -0.00068467814 | K43: 8.7000668 | L43: -0.0048154568 | M43: 0.00089969305 | N43: -5.352333 | O43: 7.2520361e-07 | P43: -0.0066042877 | Q43: -0.003026626 | R43: -0.0066042877 | S43: -0.003026626
A46: The regression results indicate a negative relationship between CAPE and future stock returns, as evidenced by the negative coefficient on CAPE. However, the predictive power is weak for 1-year returns, as the coefficient is not statistically significant, suggesting that short-term returns are largely driven by market noise. In contrast, CAPE shows stronger predictive power for 5-year returns, with a more statistically significant relationship. This suggests that valuation effects take time to materialize, as mean reversion dominates in the long run. Economically, a high CAPE ratio reflects an overvalued market, which is associated with lower future returns, while a low CAPE indicates undervaluation and higher expected returns.

Sheet Real_CAPE_Calc
A1: Year | B1: S&P Composite Price Index | C1: S&P Composite Dividends | D1: S&P Composite Earnings | E1: CPI Level (Dec 31st) | F1: 1 Year Treasury Yield (Annualized) | G1: 5 Year Treasury Yield (Annualized) | H1: S&P Composite Price Index (2024) | I1: S&P Composite Dividends (2024) | J1: S&P Composite Earnings (2024) | K1: 10-Year Avg Real Earnings | L1: Real CAPE | M1: Nominal Annual Return | N1: Real Annual Return | O1: Future 1-Year Nominal Return | P1: Future 1-Year Real Return | Q1: Future 5-Year Nominal Return | R1: Future 5-Year Real Return | T1: Previous Year CAPE | U1: S&P 500 Weight | V1: T-bill Weight | W1: Strategy Return | X1: 60/40 Benchmark Return
A2: 1922 | B2: 8.9
A3: 1923 | B3: 8.83 | C3: 0.53 | D3: 0.98 | E3: 17.3 | H3: =B3 / E3 * $E$104 -> 161.08625 | I3: =C3 / E3 * $E$104 -> 9.6688237 | J3: =D3 / E3 * $E$104 -> 17.878202 | M3: =(B3-B2+C3)/B2 -> 0.051685393 | O3: =M4 -> 0.26047565 | P3: =N4 -> 0.26047565 | Q3: =((1+M4)*(1+M5)*(1+M6)*(1+M7)*(1+M8))^(1/5)-1 -> 0.28632384 | R3: =((1+N4)*(1+N5)*(1+N6)*(1+N7)*(1+N8))^(1/5)-1 -> 0.2893188
A4: 1924 | B4: 10.58 | C4: 0.55 | D4: 0.93 | E4: 17.3 | H4: =B4 / E4 * $E$104 -> 193.01161 | I4: =C4 / E4 * $E$104 -> 10.033685 | J4: =D4 / E4 * $E$104 -> 16.966049 | M4: =(B4-B3+C4)/B3 -> 0.26047565 | N4: =(H4-H3+I4)/H3 -> 0.26047565 | O4: =M5 -> 0.25236295 | P4: =N5 -> 0.2103843 | Q4: =((1+M5)*(1+M6)*(1+M7)*(1+M8)*(1+M9))^(1/5)-1 -> 0.20579037 | R4: =((1+N5)*(1+N6)*(1+N7)*(1+N8)*(1+N9))^(1/5)-1 -> 0.2071892
A5: 1925 | B5: 12.65 | C5: 0.6 | D5: 1.25 | E5: 17.9 | H5: =B5 / E5 * $E$104 -> 223.03929 | I5: =C5 / E5 * $E$104 -> 10.578939 | J5: =D5 / E5 * $E$104 -> 22.039455 | M5: =(B5-B4+C5)/B4 -> 0.25236295 | N5: =(H5-H4+I5)/H4 -> 0.2103843 | O5: =M6 -> 0.11383399 | P5: =N6 -> 0.12641969 | Q5: =((1+M6)*(1+M7)*(1+M8)*(1+M9)*(1+M10))^(1/5)-1 -> 0.097182758 | R5: =((1+N6)*(1+N7)*(1+N8)*(1+N9)*(1+N10))^(1/5)-1 -> 0.12068718
A6: 1926 | B6: 13.4 | C6: 0.69 | D6: 1.24 | E6: 17.7 | H6: =B6 / E6 * $E$104 -> 238.9326 | I6: =C6 / E6 * $E$104 -> 12.303246 | J6: =D6 / E6 * $E$104 -> 22.110181 | M6: =(B6-B5+C6)/B5 -> 0.11383399 | N6: =(H6-H5+I6)/H5 -> 0.12641969 | O6: =M7 -> 0.36567164 | P6: =N7 -> 0.39724786 | Q6: =((1+M7)*(1+M8)*(1+M9)*(1+M10)*(1+M11))^(1/5)-1 -> -0.040160777 | R6: =((1+N7)*(1+N8)*(1+N9)*(1+N10)*(1+N11))^(1/5)-1 -> -0.0024777874
A7: 1927 | B7: 17.53 | C7: 0.77 | D7: 1.11 | E7: 17.3 | H7: =B7 / E7 * $E$104 -> 319.8009 | I7: =C7 / E7 * $E$104 -> 14.047159 | J7: =D7 / E7 * $E$104 -> 20.249801 | M7: =(B7-B6+C7)/B6 -> 0.36567164 | N7: =(H7-H6+I7)/H6 -> 0.39724786 | O7: =M8 -> 0.46662864 | P7: =N8 -> 0.48378219 | Q7: =((1+M8)*(1+M9)*(1+M10)*(1+M11)*(1+M12))^(1/5)-1 -> -0.11414637 | R7: =((1+N8)*(1+N9)*(1+N10)*(1+N11)*(1+N12))^(1/5)-1 -> -0.063480266
A8: 1928 | B8: 24.86 | C8: 0.85 | D8: 1.38 | E8: 17.1 | H8: =B8 / E8 * $E$104 -> 458.82692 | I8: =C8 / E8 * $E$104 -> 15.687968 | J8: =D8 / E8 * $E$104 -> 25.469877 | M8: =(B8-B7+C8)/B7 -> 0.46662864 | N8: =(H8-H7+I8)/H7 -> 0.48378219 | O8: =M9 -> -0.08769107 | P8: =N9 -> -0.092995192 | Q8: =((1+M9)*(1+M10)*(1+M11)*(1+M12)*(1+M13))^(1/5)-1 -> -0.1044514 | R8: =((1+N9)*(1+N10)*(1+N11)*(1+N12)*(1+N13))^(1/5)-1 -> -0.056865577
A9: 1929 | B9: 21.71 | C9: 0.97 | D9: 1.61 | E9: 17.2 | H9: =B9 / E9 * $E$104 -> 398.35957 | I9: =C9 / E9 * $E$104 -> 17.798654 | J9: =D9 / E9 * $E$104 -> 29.542096 | M9: =(B9-B8+C9)/B8 -> -0.08769107 | N9: =(H9-H8+I9)/H8 -> -0.092995192 | O9: =M10 -> -0.21879318 | P9: =N10 -> -0.1654188 | Q9: =((1+M10)*(1+M11)*(1+M12)*(1+M13)*(1+M14))^(1/5)-1 -> -0.10270241 | R9: =((1+N10)*(1+N11)*(1+N12)*(1+N13)*(1+N14))^(1/5)-1 -> -0.05676213
A10: 1930 | B10: 15.98 | C10: 0.98 | D10: 0.97 | E10: 16.1 | H10: =B10 / E10 * $E$104 -> 313.25266 | I10: =C10 / E10 * $E$104 -> 19.210739 | J10: =D10 / E10 * $E$104 -> 19.014711 | M10: =(B10-B9+C10)/B9 -> -0.21879318 | N10: =(H10-H9+I10)/H9 -> -0.1654188 | O10: =M11 -> -0.42928661 | P10: =N11 -> -0.37065167 | Q10: =((1+M11)*(1+M12)*(1+M13)*(1+M14)*(1+M15))^(1/5)-1 -> 0.027311328 | R10: =((1+N11)*(1+N12)*(1+N13)*(1+N14)*(1+N15))^(1/5)-1 -> 0.05947676
A11: 1931 | B11: 8.3 | C11: 0.82 | D11: 0.61 | E11: 14.6 | H11: =B11 / E11 * $E$104 -> 179.41928 | I11: =C11 / E11 * $E$104 -> 17.72576 | J11: =D11 / E11 * $E$104 -> 13.186236 | M11: =(B11-B10+C11)/B10 -> -0.42928661 | N11: =(H11-H10+I11)/H10 -> -0.37065167 | O11: =M12 -> -0.085542169 | P11: =N12 -> 0.019166743 | Q11: =((1+M12)*(1+M13)*(1+M14)*(1+M15)*(1+M16))^(1/5)-1 -> 0.21683711 | R11: =((1+N12)*(1+N13)*(1+N14)*(1+N15)*(1+N16))^(1/5)-1 -> 0.22709281
A12: 1932 | B12: 7.09 | C12: 0.5 | D12: 0.41 | E12: 13.1 | H12: =B12 / E12 * $E$104 -> 170.81217 | I12: =C12 / E12 * $E$104 -> 12.045992 | J12: =D12 / E12 * $E$104 -> 9.8777137 | K12: =AVERAGE(J3:J12) -> 19.633432 | L12: =H12/K12 -> 8.7000668 | M12: =(B12-B11+C12)/B11 -> -0.085542169 | N12: =(H12-H11+I12)/H11 -> 0.019166743 | O12: =M13 -> 0.54866008 | P12: =N13 -> 0.53692781 | Q12: =((1+M13)*(1+M14)*(1+M15)*(1+M16)*(1+M17))^(1/5)-1 -> 0.14967575 | R12: =((1+N13)*(1+N14)*(1+N15)*(1+N16)*(1+N17))^(1/5)-1 -> 0.12812476
A13: 1933 | B13: 10.54 | C13: 0.44 | D13: 0.44 | E13: 13.2 | F13: 0.0035 | G13: 0.0135 | H13: =B13 / E13 * $E$104 -> 252.00581 | I13: =C13 / E13 * $E$104 -> 10.520167 | J13: =D13 / E13 * $E$104 -> 10.520167 | K13: =AVERAGE(J4:J13) -> 18.897629 | L13: =H13/K13 -> 13.335314 | M13: =(B13-B12+C13)/B12 -> 0.54866008 | N13: =(H13-H12+I13)/H12 -> 0.53692781 | O13: =M14 -> -0.078747628 | P13: =N14 -> -0.092497663 | Q13: =((1+M14)*(1+M15)*(1+M16)*(1+M17)*(1+M18))^(1/5)-1 -> 0.083295871 | R13: =((1+N14)*(1+N15)*(1+N16)*(1+N17)*(1+N18))^(1/5)-1 -> 0.070622255 | T13: =L12 -> 8.7000668 | U13: =IF(T13<15,0.8,IF(T13>25,0.3,0.6)) -> 0.8 | V13: =1-U13 -> 0.2 | W13: =U13*M13+V13*F13 -> 0.43962807 | X13: =0.6*M13+0.4*F13 -> 0.33059605
A14: 1934 | B14: 9.26 | C14: 0.45 | D14: 0.49 | E14: 13.4 | F14: 0.0027833333 | G14: 0.0148 | H14: =B14 / E14 * $E$104 -> 218.09719 | I14: =C14 / E14 * $E$104 -> 10.598675 | J14: =D14 / E14 * $E$104 -> 11.54078 | K14: =AVERAGE(J5:J14) -> 18.355102 | L14: =H14/K14 -> 11.882102 | M14: =(B14-B13+C14)/B13 -> -0.078747628 | N14: =(H14-H13+I14)/H13 -> -0.092497663 | O14: =M15 -> 0.53671706 | P14: =N15 -> 0.49217454 | Q14: =((1+M15)*(1+M16)*(1+M17)*(1+M18)*(1+M19))^(1/5)-1 -> 0.10851574 | R14: =((1+N15)*(1+N16)*(1+N17)*(1+N18)*(1+N19))^(1/5)-1 -> 0.098846974 | T14: =L13 -> 13.335314 | U14: =IF(T14<15,0.8,IF(T14>25,0.3,0.6)) -> 0.8 | V14: =1-U14 -> 0.2 | W14: =U14*M14+V14*F14 -> -0.062441436 | X14: =0.6*M14+0.4*F14 -> -0.046135244
A15: 1935 | B15: 13.76 | C15: 0.47 | D15: 0.76 | E15: 13.8 | F15: 0.001675 | G15: 0.0135 | H15: =B15 / E15 * $E$104 -> 314.6902 | I15: =C15 / E15 * $E$104 -> 10.748866 | J15: =D15 / E15 * $E$104 -> 17.381145 | K15: =AVERAGE(J6:J15) -> 17.889271 | L15: =H15/K15 -> 17.591002 | M15: =(B15-B14+C15)/B14 -> 0.53671706 | N15: =(H15-H14+I15)/H14 -> 0.49217454 | O15: =M16 -> 0.3306686 | P15: =N16 -> 0.31165905 | Q15: =((1+M16)*(1+M17)*(1+M18)*(1+M19)*(1+M20))^(1/5)-1 -> -0.0012871671 | R15: =((1+N16)*(1+N17)*(1+N18)*(1+N19)*(1+N20))^(1/5)-1 -> -0.0055736465 | T15: =L14 -> 11.882102 | U15: =IF(T15<15,0.8,IF(T15>25,0.3,0.6)) -> 0.8 | V15: =1-U15 -> 0.2 | W15: =U15*M15+V15*F15 -> 0.42970865 | X15: =0.6*M15+0.4*F15 -> 0.32270024
A16: 1936 | B16: 17.59 | C16: 0.72 | D16: 1.02 | E16: 14 | F16: 0.001725 | G16: 0.0147 | H16: =B16 / E16 * $E$104 -> 396.53514 | I16: =C16 / E16 * $E$104 -> 16.231114 | J16: =D16 / E16 * $E$104 -> 22.994079 | K16: =AVERAGE(J7:J16) -> 17.97766 | L16: =H16/K16 -> 22.057105 | M16: =(B16-B15+C16)/B15 -> 0.3306686 | N16: =(H16-H15+I16)/H15 -> 0.31165905 | O16: =M17 -> -0.31154065 | P16: =N17 -> -0.33066452 | Q16: =((1+M17)*(1+M18)*(1+M19)*(1+M20)*(1+M21))^(1/5)-1 -> -0.073614896 | R16: =((1+N17)*(1+N18)*(1+N19)*(1+N20)*(1+N21))^(1/5)-1 -> -0.092282244 | T16: =L15 -> 17.591002 | U16: =IF(T16<15,0.8,IF(T16>25,0.3,0.6)) -> 0.6 | V16: =1-U16 -> 0.4 | W16: =U16*M16+V16*F16 -> 0.19909116 | X16: =0.6*M16+0.4*F16 -> 0.19909116
A17: 1937 | B17: 11.31 | C17: 0.8 | D17: 1.13 | E17: 14.4 | F17: 0.0027583333 | G17: 0.0158 | H17: =B17 / E17 * $E$104 -> 247.88143 | I17: =C17 / E17 * $E$104 -> 17.533611 | J17: =D17 / E17 * $E$104 -> 24.766226 | K17: =AVERAGE(J8:J17) -> 18.429303 | L17: =H17/K17 -> 13.450396 | M17: =(B17-B16+C17)/B16 -> -0.31154065 | N17: =(H17-H16+I17)/H16 -> -0.33066452 | O17: =M18 -> 0.15030946 | P17: =N18 -> 0.18317545 | Q17: =((1+M18)*(1+M19)*(1+M20)*(1+M21)*(1+M22))^(1/5)-1 -> 0.034569953 | R17: =((1+N18)*(1+N19)*(1+N20)*(1+N21)*(1+N22))^(1/5)-1 -> 0.0019706925 | T17: =L16 -> 22.057105 | U17: =IF(T17<15,0.8,IF(T17>25,0.3,0.6)) -> 0.6 | V17: =1-U17 -> 0.4 | W17: =U17*M17+V17*F17 -> -0.18582106 | X17: =0.6*M17+0.4*F17 -> -0.18582106
A18: 1938 | B18: 12.5 | C18: 0.51 | D18: 0.64 | E18: 14 | F18: 0.00065 | G18: 0.0127 | H18: =B18 / E18 * $E$104 -> 281.79018 | I18: =C18 / E18 * $E$104 -> 11.497039 | J18: =D18 / E18 * $E$104 -> 14.427657 | K18: =AVERAGE(J9:J18) -> 17.325081 | L18: =H18/K18 -> 16.264869 | M18: =(B18-B17+C18)/B17 -> 0.15030946 | N18: =(H18-H17+I18)/H17 -> 0.18317545 | O18: =M19 -> 0.0336 | P18: =N19 -> 0.0336 | Q18: =((1+M19)*(1+M20)*(1+M21)*(1+M22)*(1+M23))^(1/5)-1 -> 0.049354666 | R18: =((1+N19)*(1+N20)*(1+N21)*(1+N22)*(1+N23))^(1/5)-1 -> 0.0047038247 | T18: =L17 -> 13.450396 | U18: =IF(T18<15,0.8,IF(T18>25,0.3,0.6)) -> 0.8 | V18: =1-U18 -> 0.2 | W18: =U18*M18+V18*F18 -> 0.12037757 | X18: =0.6*M18+0.4*F18 -> 0.090445676
A19: 1939 | B19: 12.3 | C19: 0.62 | D19: 0.9 | E19: 14 | F19: 0.00045833333 | G19: 0.0135 | H19: =B19 / E19 * $E$104 -> 277.28154 | I19: =C19 / E19 * $E$104 -> 13.976793 | J19: =D19 / E19 * $E$104 -> 20.288893 | K19: =AVERAGE(J10:J19) -> 16.399761 | L19: =H19/K19 -> 16.907657 | M19: =(B19-B18+C19)/B18 -> 0.0336 | N19: =(H19-H18+I19)/H18 -> 0.0336 | O19: =M20 -> -0.087804878 | P19: =N20 -> -0.094274347 | Q19: =((1+M20)*(1+M21)*(1+M22)*(1+M23)*(1+M24))^(1/5)-1 -> 0.079783185 | R19: =((1+N20)*(1+N21)*(1+N22)*(1+N23)*(1+N24))^(1/5)-1 -> 0.029148788 | T19: =L18 -> 16.264869 | U19: =IF(T19<15,0.8,IF(T19>25,0.3,0.6)) -> 0.6 | V19: =1-U19 -> 0.4 | W19: =U19*M19+V19*F19 -> 0.020343333 | X19: =0.6*M19+0.4*F19 -> 0.020343333
A20: 1940 | B20: 10.55 | C20: 0.67 | D20: 1.05 | E20: 14.1 | F20: 0.00035833333 | G20: 0.0134 | H20: =B20 / E20 * $E$104 -> 236.14417 | I20: =C20 / E20 * $E$104 -> 14.996833 | J20: =D20 / E20 * $E$104 -> 23.5025 | K20: =AVERAGE(J11:J20) -> 16.84854 | L20: =H20/K20 -> 14.015705 | M20: =(B20-B19+C20)/B19 -> -0.087804878 | N20: =(H20-H19+I20)/H19 -> -0.094274347 | O20: =M21 -> -0.086255924 | P20: =N21 -> -0.16878765 | Q20: =((1+M21)*(1+M22)*(1+M23)*(1+M24)*(1+M25))^(1/5)-1 -> 0.1737943 | R20: =((1+N21)*(1+N22)*(1+N23)*(1+N24)*(1+N25))^(1/5)-1 -> 0.11537663 | T20: =L19 -> 16.907657 | U20: =IF(T20<15,0.8,IF(T20>25,0.3,0.6)) -> 0.6 | V20: =1-U20 -> 0.4 | W20: =U20*M20+V20*F20 -> -0.052539593 | X20: =0.6*M20+0.4*F20 -> -0.052539593
A21: 1941 | B21: 8.93 | C21: 0.71 | D21: 1.16 | E21: 15.5 | F21: 0.0011 | G21: 0.01478067 | H21: =B21 / E21 * $E$104 -> 181.8292 | I21: =C21 / E21 * $E$104 -> 14.456745 | J21: =D21 / E21 * $E$104 -> 23.619471 | K21: =AVERAGE(J12:J21) -> 17.891863 | L21: =H21/K21 -> 10.162676 | M21: =(B21-B20+C21)/B20 -> -0.086255924 | N21: =(H21-H20+I21)/H20 -> -0.16878765 | O21: =M22 -> 0.19596865 | P21: =N22 -> 0.096894319 | Q21: =((1+M22)*(1+M23)*(1+M24)*(1+M25)*(1+M26))^(1/5)-1 -> 0.16590922 | R21: =((1+N22)*(1+N23)*(1+N24)*(1+N25)*(1+N26))^(1/5)-1 -> 0.092052164 | T21: =L20 -> 14.015705 | U21: =IF(T21<15,0.8,IF(T21>25,0.3,0.6)) -> 0.8 | V21: =1-U21 -> 0.2 | W21: =U21*M21+V21*F21 -> -0.068784739 | X21: =0.6*M21+0.4*F21 -> -0.051313555
A22: 1942 | B22: 10.09 | C22: 0.59 | D22: 1.03 | E22: 16.9 | F22: 0.0043 | G22: 0.017288844 | H22: =B22 / E22 * $E$104 -> 188.42926 | I22: =C22 / E22 * $E$104 -> 11.018163 | J22: =D22 / E22 * $E$104 -> 19.235098 | K22: =AVERAGE(J13:J22) -> 18.827601 | L22: =H22/K22 -> 10.008139 | M22: =(B22-B21+C22)/B21 -> 0.19596865 | N22: =(H22-H21+I22)/H21 -> 0.096894319 | O22: =M23 -> 0.23488603 | P22: =N23 -> 0.1994008 | Q22: =((1+M23)*(1+M24)*(1+M25)*(1+M26)*(1+M27))^(1/5)-1 -> 0.13164116 | R22: =((1+N23)*(1+N24)*(1+N25)*(1+N26)*(1+N27))^(1/5)-1 -> 0.060334527 | T22: =L21 -> 10.162676 | U22: =IF(T22<15,0.8,IF(T22>25,0.3,0.6)) -> 0.8 | V22: =1-U22 -> 0.2 | W22: =U22*M22+V22*F22 -> 0.15763492 | X22: =0.6*M22+0.4*F22 -> 0.11930119
A23: 1943 | B23: 11.85 | C23: 0.61 | D23: 0.94 | E23: 17.4 | F23: 0.0084 | G23: 0.016500042 | H23: =B23 / E23 * $E$104 -> 214.93789 | I23: =C23 / E23 * $E$104 -> 11.064313 | J23: =D23 / E23 * $E$104 -> 17.049925 | K23: =AVERAGE(J14:J23) -> 19.480577 | L23: =H23/K23 -> 11.033446 | M23: =(B23-B22+C23)/B22 -> 0.23488603 | N23: =(H23-H22+I23)/H22 -> 0.1994008 | O23: =M24 -> 0.19240506 | P23: =N24 -> 0.16560944 | Q23: =((1+M24)*(1+M25)*(1+M26)*(1+M27)*(1+M28))^(1/5)-1 -> 0.10545061 | R23: =((1+N24)*(1+N25)*(1+N26)*(1+N27)*(1+N28))^(1/5)-1 -> 0.035728165 | T23: =L22 -> 10.008139 | U23: =IF(T23<15,0.8,IF(T23>25,0.3,0.6)) -> 0.8 | V23: =1-U23 -> 0.2 | W23: =U23*M23+V23*F23 -> 0.18958882 | X23: =0.6*M23+0.4*F23 -> 0.14429162
A24: 1944 | B24: 13.49 | C24: 0.64 | D24: 0.93 | E24: 17.8 | F24: 0.0087 | G24: 0.014987802 | H24: =B24 / E24 * $E$104 -> 239.18604 | I24: =C24 / E24 * $E$104 -> 11.347596 | J24: =D24 / E24 * $E$104 -> 16.489475 | K24: =AVERAGE(J15:J24) -> 19.975447 | L24: =H24/K24 -> 11.974002 | M24: =(B24-B23+C24)/B23 -> 0.19240506 | N24: =(H24-H23+I24)/H23 -> 0.16560944 | O24: =M25 -> 0.38472943 | P24: =N25 -> 0.35429582 | Q24: =((1+M25)*(1+M26)*(1+M27)*(1+M28)*(1+M29))^(1/5)-1 -> 0.10186223 | R24: =((1+N25)*(1+N26)*(1+N27)*(1+N28)*(1+N29))^(1/5)-1 -> 0.041427153 | T24: =L23 -> 11.033446 | U24: =IF(T24<15,0.8,IF(T24>25,0.3,0.6)) -> 0.8 | V24: =1-U24 -> 0.2 | W24: =U24*M24+V24*F24 -> 0.15566405 | X24: =0.6*M24+0.4*F24 -> 0.11892304
... A99: 2019 | B99: 3176.7495 | C99: 58.24 | D99: 139.47 | E99: 256.974 | F99: 0.0266 | G99: 0.0268 | H99: =B99 / E99 * $E$104 -> 3901.5544 | I99: =C99 / E99 * $E$104 -> 71.527996 | J99: =D99 / E99 * $E$104 -> 171.29137 | K99: =AVERAGE(J90:J99) -> 134.24343 | L99: =H99/K99 -> 29.063279 | M99: =(B99-B98+C99)/B98 -> 0.26006969 | N99: =(H99-H98+I99)/H98 -> 0.23191875 | O99: =M100 -> 0.18158162 | P99: =N100 -> 0.16570466 | Q99: =((1+M100)*(1+M101)*(1+M102)*(1+M103)*(1+M104))^(1/5)-1 -> 0.15267565 | R99: =((1+N100)*(1+N101)*(1+N102)*(1+N103)*(1+N104))^(1/5)-1 -> 0.10625738 | T99: =L98 -> 25.891359 | U99: =IF(T99<15,0.8,IF(T99>25,0.3,0.6)) -> 0.3 | V99: =1-U99 -> 0.7 | W99: =U99*M99+V99*F99 -> 0.096640908 | X99: =0.6*M99+0.4*F99 -> 0.16668182
A100: 2020 | B100: 3695.31 | C100: 58.278846 | D100: 94.13 | E100: 260.474 | F100: 0.0155 | G100: 0.0168 | H100: =B100 / E100 * $E$104 -> 4477.4462 | I100: =C100 / E100 * $E$104 -> 70.613939 | J100: =D100 / E100 * $E$104 -> 114.05322 | K100: =AVERAGE(J91:J100) -> 134.51081 | L100: =H100/K100 -> 33.286888 | M100: =(B100-B99+C100)/B99 -> 0.18158162 | N100: =(H100-H99+I100)/H99 -> 0.16570466 | O100: =M101 -> 0.28139989 | P100: =N101 -> 0.1971627 | T100: =L99 -> 29.063279 | U100: =IF(T100<15,0.8,IF(T100>25,0.3,0.6)) -> 0.3 | V100: =1-U100 -> 0.7 | W100: =U100*M100+V100*F100 -> 0.065324486 | X100: =0.6*M100+0.4*F100 -> 0.11514897
A101: 2021 | B101: 4674.7727 | C101: 60.397117 | D101: 197.87 | E101: 278.802 | F101: 0.001 | G101: 0.0036 | H101: =B101 / E101 * $E$104 -> 5291.8618 | I101: =C101 / E101 * $E$104 -> 68.369783 | J101: =D101 / E101 * $E$104 -> 223.98965 | K101: =AVERAGE(J92:J101) -> 144.74971 | L101: =H101/K101 -> 36.558704 | M101: =(B101-B100+C101)/B100 -> 0.28139989 | N101: =(H101-H100+I101)/H100 -> 0.1971627 | O101: =M102 -> -0.14877125 | P101: =N102 -> -0.20038182 | T101: =L100 -> 33.286888 | U101: =IF(T101<15,0.8,IF(T101>25,0.3,0.6)) -> 0.3 | V101: =1-U101 -> 0.7 | W101: =U101*M101+V101*F101 -> 0.085119968 | X101: =0.6*M101+0.4*F101 -> 0.16923994
A102: 2022 | B102: 3912.381 | C102: 66.92 | D102: 172.75 | E102: 296.797 | F102: 0.004 | G102: 0.0127 | H102: =B102 / E102 * $E$104 -> 4160.3082 | I102: =C102 / E102 * $E$104 -> 71.160715 | J102: =D102 / E102 * $E$104 -> 183.69715 | K102: =AVERAGE(J93:J102) -> 151.22793 | L102: =H102/K102 -> 27.510184 | M102: =(B102-B101+C102)/B101 -> -0.14877125 | N102: =(H102-H101+I102)/H101 -> -0.20038182 | O102: =M103 -> 0.21546323 | P102: =N103 -> 0.1760409 | T102: =L101 -> 36.558704 | U102: =IF(T102<15,0.8,IF(T102>25,0.3,0.6)) -> 0.3 | V102: =1-U102 -> 0.7 | W102: =U102*M102+V102*F102 -> -0.041831375 | X102: =0.6*M102+0.4*F102 -> -0.087662749
A103: 2023 | B103: 4685.0515 | C103: 70.303692 | D103: 192.43 | E103: 306.746 | F103: 0.0471 | G103: 0.0399 | H103: =B103 / E103 * $E$104 -> 4820.3585 | I103: =C103 / E103 * $E$104 -> 72.334103 | J103: =D103 / E103 * $E$104 -> 197.98749 | K103: =AVERAGE(J94:J103) -> 157.45716 | L103: =H103/K103 -> 30.613777 | M103: =(B103-B102+C103)/B102 -> 0.21546323 | N103: =(H103-H102+I103)/H102 -> 0.1760409 | O103: =M104 -> 0.29896989 | P103: =N104 -> 0.26250794 | T103: =L102 -> 27.510184 | U103: =IF(T103<15,0.8,IF(T103>25,0.3,0.6)) -> 0.3 | V103: =1-U103 -> 0.7 | W103: =U103*M103+V103*F103 -> 0.097608969 | X103: =0.6*M103+0.4*F103 -> 0.14811794
A104: 2024 | B104: 6010.9086 | C104: 74.832255 | D104: 210.17 | E104: 315.605 | F104: 0.0479 | G104: 0.039 | H104: =B104 / E104 * $E$104 -> 6010.9086 | I104: =C104 / E104 * $E$104 -> 74.832255 | J104: =D104 / E104 * $E$104 -> 210.17 | K104: =AVERAGE(J95:J104) -> 164.72293 | L104: =H104/K104 -> 36.491025 | M104: =(B104-B103+C104)/B103 -> 0.29896989 | N104: =(H104-H103+I104)/H103 -> 0.26250794 | T104: =L103 -> 30.613777 | U104: =IF(T104<15,0.8,IF(T104>25,0.3,0.6)) -> 0.3 | V104: =1-U104 -> 0.7 | W104: =U104*M104+V104*F104 -> 0.12322097 | X104: =0.6*M104+0.4*F104 -> 0.19854193
A105: Average | L105: =AVERAGE(L12:L104) -> 18.962843 | M105: =AVERAGE(M3:M104) -> 0.12151589 | N105: =AVERAGE(N4:N104) -> 0.091047917 | T105: =AVERAGE(T13:T104) -> 18.772319 | U105: =AVERAGE(U13:U104) -> 0.60108696 | V105: =AVERAGE(V13:V104) -> 0.39891304 | W105: =AVERAGE(W13:W104) -> 0.097397241 | X105: =AVERAGE(X13:X104) -> 0.091293139
T108: Based on the regression results, CAPE has a negative relationship with future returns and stronger predictive power over longer horizons. Therefore, I use the previous year’s CAPE ratio as a signal for asset allocation. When CAPE is low, indicating undervaluation, I allocate 80% to the S&P 500 and 20% to Treasury bills. When CAPE is between 15 and 25, I allocate 60% to equities and 40% to Treasury bills. When CAPE is high, indicating overvaluation, I reduce equity exposure to 30% and invest 70% in Treasury bills. This strategy is based on the idea that investors should increase equity exposure when the market is undervalued and reduce exposure when it is overvalued. Based on my calculations, the strategy generates an average return of about 4%, compared to about 3% for the static 60/40 benchmark. Therefore, the CAPE-based market-timing strategy slightly outperforms the benchmark.

Sheet CAPE vs 1-Year Return

Sheet CAPE vs 5-Year Return

Sheet Portfolio Growth
A1: Year | B1: CAPE Strategy | C1: 60/40 Benchmark | E1: Growth of $1 Invested: CAPE Dynamic Allocation Strategy vs. 60/40 Benchmark (1932–2024)
A2: 1932 | B2: 1 | C2: 1
A3: 1933 | B3: =B2*(1+'RAW Data'!W13) -> 1.4396281 | C3: =C2*(1+'RAW Data'!X13) -> 1.3305961
A4: 1934 | B4: =B3*(1+'RAW Data'!W14) -> 1.3497356 | C4: =C3*(1+'RAW Data'!X14) -> 1.2692087
A5: 1935 | B5: =B4*(1+'RAW Data'!W15) -> 1.9297287 | C5: =C4*(1+'RAW Data'!X15) -> 1.6787826
A6: 1936 | B6: =B5*(1+'RAW Data'!W16) -> 2.3139206 | C6: =C5*(1+'RAW Data'!X16) -> 2.0130134
A7: 1937 | B7: =B6*(1+'RAW Data'!W17) -> 1.8839455 | C7: =C6*(1+'RAW Data'!X17) -> 1.6389531
A8: 1938 | B8: =B7*(1+'RAW Data'!W18) -> 2.1107302 | C8: =C7*(1+'RAW Data'!X18) -> 1.7871894
A9: 1939 | B9: =B8*(1+'RAW Data'!W19) -> 2.1536695 | C9: =C8*(1+'RAW Data'!X19) -> 1.8235467
A10: 1940 | B10: =B9*(1+'RAW Data'!W20) -> 2.0405166 | C10: =C9*(1+'RAW Data'!X20) -> 1.7277383
A11: 1941 | B11: =B10*(1+'RAW Data'!W21) -> 1.9001602 | C11: =C10*(1+'RAW Data'!X21) -> 1.6390819
A12: 1942 | B12: =B11*(1+'RAW Data'!W22) -> 2.1996918 | C12: =C11*(1+'RAW Data'!X22) -> 1.8346264
A13: 1943 | B13: =B12*(1+'RAW Data'!W23) -> 2.6167288 | C13: =C12*(1+'RAW Data'!X23) -> 2.0993476
A14: 1944 | B14: =B13*(1+'RAW Data'!W24) -> 3.0240594 | C14: =C13*(1+'RAW Data'!X24) -> 2.3490084
... A94: 2024 | B94: =B93*(1+'RAW Data'!W104) -> 3128.8992 | C94: =C93*(1+'RAW Data'!X104) -> 1995.3031
